{
   "dispatch": [],
   "global": [],
   "meta": {},
   "rules": [{
      "actions": [{"action": {
         "args": [
            {
               "type": "str",
               "val": "test"
            },
            {
               "type": "str",
               "val": "test"
            }
         ],
         "modifiers": null,
         "name": "replace",
         "source": null
      }}],
      "blocktype": "every",
      "callbacks": null,
      "cond": {
         "type": "bool",
         "val": "true"
      },
      "emit": null,
      "foreach": [],
      "name": "test0",
      "pagetype": {"event_expr": {
         "legacy": 1,
         "op": "pageview",
         "pattern": "/test/",
         "type": "prim_event",
         "vars": []
      }},
      "pre": [{
         "lhs": "foo",
         "rhs": "\n$K(\"#foo\").after(#{x});\n",
         "type": "JS"
      }],
      "state": "active"
   }],
   "ruleset_name": "10"
}
